tlib/__init__.py
tlib/traceback_util.py
tlib/tree_util.py
tlib/backend/__init__.py
tlib/backend/_triton.py
tlib/backend/base.py
tlib/backend/register.py
tlib/expr/__init__.py
tlib/expr/solver.py
tlib/expr/stage1.py
tlib/expr/stage2.py
tlib/expr/stage3.py
tlib/expr/util.py
tlib/functional/__init__.py
tlib/functional/activations.py
tlib/functional/base.py
tlib/functional/binary.py
tlib/functional/reductions.py
tlib/functional/unary.py
tlib/nn/__init__.py
tlib/nn/layernorms.py
tlib/ops/__init__.py
tlib/ops/arange.py
tlib/ops/binary.py
tlib/ops/dot.py
tlib/ops/rearrange.py
tlib/ops/reduce.py
tlib/ops/solve.py
tlib/ops/unary.py
tlib/ops/util.py
tlib/ops/vmap_with_axis.py
tlib/tracer/__init__.py
tlib/tracer/compile.py
tlib/tracer/decorator.py
tlib/tracer/input.py
tlib/tracer/optimize.py
tlib/tracer/tensor.py
tlib/tracer/tracer.py
triton_lib-0.0.1.dist-info/licenses/LICENSE
triton_lib-0.0.1.dist-info/METADATA
triton_lib-0.0.1.dist-info/WHEEL
triton_lib-0.0.1.dist-info/top_level.txt
triton_lib-0.0.1.dist-info/RECORD
