Metadata-Version: 2.4
Name: triton-lib
Version: 0.0.1
Summary: Add your description here
Author-email: hprairie <hprairie17@gmail.com>
Requires-Python: <3.14,>=3.12
License-File: LICENSE
Requires-Dist: frozendict>=2.4.6
Requires-Dist: numpy>=2.3.1
Requires-Dist: sympy>=1.14.0
Requires-Dist: triton>=3.4.0
Provides-Extra: test
Requires-Dist: pytest>=8.0.0; extra == "test"
Requires-Dist: torch>=2.8.0; extra == "test"
Requires-Dist: pytest-cov>=4.0.0; extra == "test"
Requires-Dist: pytest-xdist>=3.0.0; extra == "test"
Requires-Dist: pytest-benchmark>=4.0.0; extra == "test"
Provides-Extra: dev
Requires-Dist: black>=24.0.0; extra == "dev"
Dynamic: license-file
